cfdiclient/__init__.py
cfdiclient/autenticacion.py
cfdiclient/autenticacion.xml
cfdiclient/descargamasiva.py
cfdiclient/descargamasiva.xml
cfdiclient/fiel.py
cfdiclient/signer.py
cfdiclient/signer.xml
cfdiclient/solicitadescargaEmitidos.py
cfdiclient/solicitadescargaEmitidos.xml
cfdiclient/solicitadescargaRecibidos.py
cfdiclient/solicitadescargaRecibidos.xml
cfdiclient/utils.py
cfdiclient/validacioncfdi.py
cfdiclient/verificasolicituddescarga.py
cfdiclient/verificasolicituddescarga.xml
cfdiclient/webservicerequest.py
tests/__init__.py
tests/test_cfdiclient.py
cfdiclient-1.6.2.dist-info/LICENSE
cfdiclient-1.6.2.dist-info/METADATA
cfdiclient-1.6.2.dist-info/WHEEL
cfdiclient-1.6.2.dist-info/top_level.txt
cfdiclient-1.6.2.dist-info/RECORD
