Metadata-Version: 2.1
Name: cfdiclient
Version: 1.6.2
Summary: Cliente Python Web Service del SAT para la descarga masiva de CFDIs
Home-page: https://github.com/luisiturrios1/python-cfdiclient
Author: Luis Iturrios
Author-email: luisiturrios1@gmail.com
Classifier: Programming Language :: Python :: 2.7
Classifier: Programming Language :: Python :: 3.6
Classifier: Programming Language :: Python :: 3.7
Classifier: Programming Language :: Python :: 3.8
Classifier: Programming Language :: Python :: 3.9
Classifier: License :: OSI Approved :: GNU General Public License v3 (GPLv3)
Classifier: Operating System :: OS Independent
License-File: LICENSE
Requires-Dist: lxml>=4.2.5
Requires-Dist: requests>=2.21.0
Requires-Dist: pycryptodome>=3.7.2
Requires-Dist: pyOpenSSL>=18.0.0
